performance_logger/__init__.py
performance_logger/logger.py
performance_logger/main.py
performance_logger/test.py
performance_logger-1.0.3.dist-info/LICENSE
performance_logger-1.0.3.dist-info/METADATA
performance_logger-1.0.3.dist-info/WHEEL
performance_logger-1.0.3.dist-info/top_level.txt
performance_logger-1.0.3.dist-info/RECORD
