Metadata-Version: 2.1
Name: performance-logger
Version: 1.0.3
Summary: check performance of the func using decorator
Home-page: UNKNOWN
Author: Sean Kim
Author-email: ddhyun93@gmail.com
License: UNKNOWN
Keywords: performance_logger
Platform: UNKNOWN
Classifier: Programming Language :: Python :: 3
Classifier: License :: OSI Approved :: MIT License
Classifier: Operating System :: OS Independent
Requires-Python: >=3
License-File: LICENSE
Requires-Dist: logger
